aws_cdk/cloud_assembly_schema/__init__.py
aws_cdk/cloud_assembly_schema/py.typed
aws_cdk/cloud_assembly_schema/_jsii/__init__.py
aws_cdk/cloud_assembly_schema/_jsii/cloud-assembly-schema@50.0.0.jsii.tgz
aws_cdk_cloud_assembly_schema-50.0.0.dist-info/LICENSE
aws_cdk_cloud_assembly_schema-50.0.0.dist-info/METADATA
aws_cdk_cloud_assembly_schema-50.0.0.dist-info/NOTICE
aws_cdk_cloud_assembly_schema-50.0.0.dist-info/WHEEL
aws_cdk_cloud_assembly_schema-50.0.0.dist-info/top_level.txt
aws_cdk_cloud_assembly_schema-50.0.0.dist-info/RECORD
